{
  "type": "FeatureCollection",
  "features": [
    {
      "type": "Feature",
      "geometry": {
        "type": "Point",
        "coordinates": [ 	
          23.1136,
          -82.3666
        ]
      },
      "properties": {
        "City": "Havana",
        "PlaceInfo": "Relevant post <b><a href='/12-days-in-cuba-part-1-havana/'>12 days in Cuba – Part 1 | Havana</a></b>"
      }
    },
    {
      "type": "Feature",
      "geometry": {
        "type": "Point",
        "coordinates": [ 	
          -79.9808,
          21.796
        ]
      },
      "properties": {
        "City": "Trinidad",
        "PlaceInfo": "Relevant post <b><a href='/12-days-in-cuba-part-2-cienfuegos-trinidad/'>12 days in Cuba – Part 2 | Cienfuegos & Trinidad</a></b>"
      }
    },
    {
      "type": "Feature",
      "geometry": {
        "type": "Point",
        "coordinates": [ 	
          -83.7066,
          22.6188
        ]
      },
      "properties": {
        "City": "Viñales",
        "PlaceInfo": "Relevant post <b><a href='/12-days-in-cuba-part-3-vinales-havana/'>12 days in Cuba – Part 3 | Viñales & Havana</a></b>"
      }
    }        
  ]
}