{
  "type": "FeatureCollection",
  "features": [
    {
      "type": "Feature",
      "geometry": {
        "type": "Point",
        "coordinates": [ 	
          10.7522,
          59.9139
        ]
      },
      "properties": {
        "City": "Oslo",
        "PlaceInfo": "Relevant post <b><a href='/november-in-oslo-and-copenhagen/'>November in Oslo and Copenhagen</a></b>"
      }
    }
  ]
}